foo_et_al_JK/__init__.py
foo_et_al_JK/foo_et_al.py
foo_et_al_JK/sphere.py
foo_et_al_JK-0.0.1.dist-info/LICENSE
foo_et_al_JK-0.0.1.dist-info/METADATA
foo_et_al_JK-0.0.1.dist-info/WHEEL
foo_et_al_JK-0.0.1.dist-info/top_level.txt
foo_et_al_JK-0.0.1.dist-info/RECORD
