Metadata-Version: 2.1
Name: foo_et_al_JK
Version: 0.0.1
Summary: A small package that calculates the Foo et al. parameterization
Author: Joseph Kim
Author-email: Joseph Kim <josephhkim0112@gmail.com>
Project-URL: Homepage, https://github.com/JosephK011/foo
Classifier: Programming Language :: Python :: 3
Classifier: License :: OSI Approved :: MIT License
Classifier: Operating System :: OS Independent
Requires-Python: >=3.8
License-File: LICENSE
